[
    {
        "productId": 1,
        "productName": "asdwas1",
        "productPrice": 50,
        "inventry":10
    },
    {
        "productId": 2,
        "productName": "dasdasdas",
        "productPrice": 100,
        "inventry":30
    },
    {
        "productId": 3,
        "productName": "proascasduct3",
        "productPrice": 200,
        "inventry":15
    },
    {
        "productId": 4,
        "productName": "producdasdasdt4",
        "productPrice": 300,
        "inventry":10
    }
]